tenzir_common/__init__.py
tenzir_common/arrow.py
tenzir_common/config.py
tenzir_common/logging.py
tenzir_common-5.25.1.dist-info/WHEEL
tenzir_common-5.25.1.dist-info/METADATA
tenzir_common-5.25.1.dist-info/RECORD
