Metadata-Version: 2.4
Name: tenzir-common
Version: 5.25.1
Summary: Shared Python utilities for the Tenzir data pipeline
Author: Tenzir
Author-email: Tenzir <engineering@tenzir.com>
License-Expression: BSD-3-Clause
Classifier: Development Status :: 3 - Alpha
Classifier: Operating System :: MacOS :: MacOS X
Classifier: Operating System :: POSIX :: Linux
Requires-Dist: pyarrow>=11
Requires-Dist: dynaconf>=3.2
Requires-Dist: pandas>=2.1.3
Requires-Python: >=3.9
